batchllm/__init__.py
batchllm/executor.py
batchllm/util.py
kernels/example.py
batchllm-0.2.7.dist-info/LICENSE
batchllm-0.2.7.dist-info/METADATA
batchllm-0.2.7.dist-info/WHEEL
batchllm-0.2.7.dist-info/top_level.txt
batchllm-0.2.7.dist-info/RECORD
