Metadata-Version: 2.1
Name: batchllm
Version: 0.2.7
Summary: A framework designed for llm offline distributed inference from Odps datasource.
Author-email: "chaofeng.gcf" <chaofeng.gcf@alibaba-inc.com>
Project-URL: Homepage, https://github.com/Lyaction/BatchLLM
Project-URL: Issues, https://github.com/Lyaction/BatchLLM/issues
Classifier: Programming Language :: Python :: 3
Classifier: License :: OSI Approved :: MIT License
Classifier: Operating System :: OS Independent
Requires-Python: >=3.10
License-File: LICENSE
